Metadata-Version: 2.4
Name: image_processing_estevaomgouveia
Version: 0.0.1
Summary: Image Processing Package using Skimage
Home-page: https://github.com/tiemi/image-processing-package
Author: Estevão
Requires-Python: >=3.5
Requires-Dist: matplotlib
Requires-Dist: numpy
Requires-Dist: scikit-image>=0.16.1
Dynamic: author
Dynamic: description
Dynamic: description-content-type
Dynamic: home-page
Dynamic: requires-dist
Dynamic: requires-python
Dynamic: summary
